LICENSE.md
MANIFEST.in
README.md
VERSION.txt
requirements.txt
setup.py
woudc_formats/PI_list.txt
woudc_formats/__init__.py
woudc_formats/resource.cfg
woudc_formats/totalozone_mf.py
woudc_formats/util.py
woudc_formats.egg-info/PKG-INFO
woudc_formats.egg-info/SOURCES.txt
woudc_formats.egg-info/dependency_links.txt
woudc_formats.egg-info/entry_points.txt
woudc_formats.egg-info/requires.txt
woudc_formats.egg-info/top_level.txt