Metadata-Version: 1.1
Name: woudc-formats
Version: 0.2.0
Summary: Python library for converting non-standard formats to WOUDC extended CSV format
Home-page: https://github.com/woudc/woudc-formats
Author: Meteorological Service of Canada, Environment Canada
Author-email: ec.woudc.ec@canada.ca
License: MIT
Keywords: Ozone O3 Ultraviolet Radiation UV UV Index Dobson Units Archives World Data Centre WOUDC Non-standard FormatSHADOZ AMES BAS Masterfile
Platform: all
Classifier: Development Status :: 4 - Beta
Classifier: Environment :: Console
Classifier: Intended Audience :: Developers
Classifier: Intended Audience :: Science/Research
Classifier: License :: OSI Approved :: MIT License
Classifier: Operating System :: OS Independent
Classifier: Programming Language :: Python
Classifier: Topic :: Scientific/Engineering :: Atmospheric Science
